MANIFEST.in
setup.py
django_elements.egg-info/PKG-INFO
django_elements.egg-info/SOURCES.txt
django_elements.egg-info/dependency_links.txt
django_elements.egg-info/not-zip-safe
django_elements.egg-info/requires.txt
django_elements.egg-info/top_level.txt
elements/__init__.py
elements/admin.py
elements/markup.py
elements/models.py
elements/settings.py
elements/tests.py
elements/views.py
elements/extensions/__init__.py
elements/extensions/mdx_subscript.py
elements/extensions/mdx_superscript.py
elements/static/elements/markitup/markdown/set.js
elements/static/elements/markitup/markdown/style.css
elements/static/elements/markitup/markdown/images/bold.png
elements/static/elements/markitup/markdown/images/brick_add.png
elements/static/elements/markitup/markdown/images/code.png
elements/static/elements/markitup/markdown/images/h1.png
elements/static/elements/markitup/markdown/images/h2.png
elements/static/elements/markitup/markdown/images/h3.png
elements/static/elements/markitup/markdown/images/h4.png
elements/static/elements/markitup/markdown/images/h5.png
elements/static/elements/markitup/markdown/images/h6.png
elements/static/elements/markitup/markdown/images/italic.png
elements/static/elements/markitup/markdown/images/link.png
elements/static/elements/markitup/markdown/images/list-bullet.png
elements/static/elements/markitup/markdown/images/list-numeric.png
elements/static/elements/markitup/markdown/images/picture.png
elements/static/elements/markitup/markdown/images/preview.png
elements/static/elements/markitup/markdown/images/quotes.png
elements/templates/elements/custom.html
elements/templates/elements/default.html
elements/templatetags/__init__.py
elements/templatetags/elements_markup.py