Metadata-Version: 1.0
Name: django-elements
Version: 0.1.1
Summary: Enhanced Markdown editing for Django projects.
Home-page: https://github.com/wnielson/django-elements
Author: Weston Nielson
Author-email: wnielson@github
License: MIT
Keywords: django markdown macros
Platform: UNKNOWN
